libf0/__init__.py
libf0/pyin.py
libf0/salience.py
libf0/swipe.py
libf0/swipe_slim.py
libf0/utils.py
libf0/yin.py
libf0-1.1.1.dist-info/METADATA
libf0-1.1.1.dist-info/WHEEL
libf0-1.1.1.dist-info/licenses/LICENCE
libf0-1.1.1.dist-info/RECORD
