Metadata-Version: 2.4
Name: libf0
Version: 1.1.1
Summary: A Python Library for Fundamental Frequency Estimation in Music Recordings
License-Expression: MIT
License-File: LICENCE
Author: Sebastian Rosenzweig
Author-email: sebastian.rosenzweig@audiolabs-erlangen.de
Requires-Python: >=3.10
Classifier: Programming Language :: Python :: 3
Classifier: Programming Language :: Python :: 3.10
Classifier: Programming Language :: Python :: 3.11
Classifier: Programming Language :: Python :: 3.12
Classifier: Programming Language :: Python :: 3.13
Classifier: Programming Language :: Python :: 3.14
Requires-Dist: librosa (>=0.11)
Requires-Dist: numba (>=0.63)
Requires-Dist: numpy (>=2.2)
Requires-Dist: scipy (>=1.15)
